<clientscript scriptid="customscript_nspsw_ue_store_avg_cost">
  <description></description>
  <isinactive>F</isinactive>
  <name>NSPSW | CS | Store Average Cost</name>
  <notifyadmins>F</notifyadmins>
  <notifyemails></notifyemails>
  <notifyowner>T</notifyowner>
  <notifyuser>F</notifyuser>
  <scriptfile>[/SuiteScripts/nspsw_store_average_cost/nspsw_cs_store_avg_cost.js]</scriptfile>
  <scriptdeployments>
    <scriptdeployment scriptid="customdeploy_nspsw_cs_item_fulfillment">
      <allemployees>T</allemployees>
      <alllocalizationcontexts>T</alllocalizationcontexts>
      <allpartners>F</allpartners>
      <allroles>T</allroles>
      <audslctrole>CUSTOMER_CENTER|EMPLOYEE_CENTER|NETSUITE_SUPPORT_CENTER__BASIC|NETSUITE_SUPPORT_CENTER|ONLINE_FORM_USER|PARTNER_CENTER|VENDOR_CENTER</audslctrole>
      <eventtype></eventtype>
      <executioncontext>ACTION|ADVANCEDREVREC|BANKCONNECTIVITY|BANKSTATEMENTPARSER|BUNDLEINSTALLATION|CLIENT|CONSOLRATEADJUSTOR|CSVIMPORT|CUSTOMGLLINES|CUSTOMMASSUPDATE|DATASETBUILDER|DEBUGGER|EMAILCAPTURE|FICONNECTIVITY|FIPARSER|MAPREDUCE|OCRPLUGIN|OTHER|PAYMENTGATEWAY|PAYMENTPOSTBACK|PLATFORMEXTENSION|PORTLET|PROMOTIONS|RECORDACTION|RESTLET|RESTWEBSERVICES|SCHEDULED|SDFINSTALLATION|SHIPPINGPARTNERS|SUITELET|TAXCALCULATION|USEREVENT|USERINTERFACE|WEBSERVICES|WORKBOOKBUILDER|WORKFLOW</executioncontext>
      <isdeployed>T</isdeployed>
      <loglevel>DEBUG</loglevel>
      <recordtype>SALESORDER</recordtype>
      <status>TESTING</status>
    </scriptdeployment>
  </scriptdeployments>
</clientscript>