<centertab scriptid="custcentertab1250">
  <allcustomers>F</allcustomers>
  <allemployees>F</allemployees>
  <allpartners>F</allpartners>
  <allroles>T</allroles>
  <allvendors>F</allvendors>
  <audslctrole></audslctrole>
  <center>[scriptid=custcenter253]</center>
  <label>Calendar</label>
  <portlets>
    <portlet scriptid="portlet_22618_662377_181">
      <isportletshown>T</isportletshown>
      <portlet>CALENDAR</portlet>
      <portletcolumn>1</portletcolumn>
    </portlet>
    <portlet scriptid="portlet_22610_662377_181">
      <isportletshown>T</isportletshown>
      <portlet>QUICKSEARCH</portlet>
      <portletcolumn>1</portletcolumn>
    </portlet>
    <portlet scriptid="portlet_22617_662377_181">
      <isportletshown>T</isportletshown>
      <portlet>QUICKADD</portlet>
      <portletcolumn>1</portletcolumn>
    </portlet>
    <portlet scriptid="portlet_22624_662377_181">
      <isportletshown>T</isportletshown>
      <portlet>TASKLINKS</portlet>
      <portletcolumn>1</portletcolumn>
    </portlet>
    <portlet scriptid="portlet_22622_662377_181">
      <isportletshown>T</isportletshown>
      <portlet>CALENDAR</portlet>
      <portletcolumn>2</portletcolumn>
    </portlet>
    <portlet scriptid="portlet_22614_662377_181">
      <isportletshown>F</isportletshown>
      <portlet>LIST</portlet>
      <portletcolumn>2</portletcolumn>
    </portlet>
    <portlet scriptid="portlet_22609_662377_181">
      <isportletshown>F</isportletshown>
      <portlet>LIST</portlet>
      <portletcolumn>2</portletcolumn>
    </portlet>
    <portlet scriptid="portlet_22619_662377_181">
      <isportletshown>T</isportletshown>
      <portlet>SCHEDULER</portlet>
      <portletcolumn>2</portletcolumn>
    </portlet>
    <portlet scriptid="portlet_22607_662377_181">
      <isportletshown>T</isportletshown>
      <portlet>SEARCHRESULTS</portlet>
      <portletcolumn>2</portletcolumn>
    </portlet>
    <portlet scriptid="portlet_22603_662377_181">
      <isportletshown>T</isportletshown>
      <portlet>SEARCHRESULTS</portlet>
      <portletcolumn>2</portletcolumn>
    </portlet>
  </portlets>
</centertab>