<usereventscript scriptid="customscript_ue_tran_bopis_check">
  <description>User event for transactions that will check to see if the shipping item selected is tied to a BOPIS record which will change the shipping address to the location</description>
  <isinactive>F</isinactive>
  <name>NS|UE|Transaction BOPIS Check</name>
  <notifyadmins>F</notifyadmins>
  <notifyemails></notifyemails>
  <notifyowner>T</notifyowner>
  <notifyuser>F</notifyuser>
  <scriptfile>[/SuiteScripts/_nscs/bopis-taxation/nscs_ue_transaction_bopis_check.js]</scriptfile>
  <scriptdeployments>
    <scriptdeployment scriptid="customdeploy_ue_tran_bopis_check_cs">
      <allemployees>F</allemployees>
      <alllocalizationcontexts>T</alllocalizationcontexts>
      <allpartners>F</allpartners>
      <allroles>T</allroles>
      <audslctrole>CUSTOMER_CENTER|EMPLOYEE_CENTER|NETSUITE_SUPPORT_CENTER__BASIC|NETSUITE_SUPPORT_CENTER|ONLINE_FORM_USER|PARTNER_CENTER|VENDOR_CENTER</audslctrole>
      <eventtype></eventtype>
      <executioncontext>ACTION|ADVANCEDREVREC|BANKCONNECTIVITY|BANKSTATEMENTPARSER|BUNDLEINSTALLATION|CLIENT|CONSOLRATEADJUSTOR|CSVIMPORT|CUSTOMGLLINES|CUSTOMMASSUPDATE|DATASETBUILDER|DEBUGGER|EMAILCAPTURE|FICONNECTIVITY|FIPARSER|MAPREDUCE|OCRPLUGIN|OTHER|PAYMENTGATEWAY|PAYMENTPOSTBACK|PLATFORMEXTENSION|PORTLET|PROMOTIONS|RECORDACTION|RESTLET|RESTWEBSERVICES|SCHEDULED|SDFINSTALLATION|SHIPPINGPARTNERS|SUITELET|TAXCALCULATION|USEREVENT|USERINTERFACE|WEBSERVICES|WORKBOOKBUILDER|WORKFLOW</executioncontext>
      <isdeployed>T</isdeployed>
      <loglevel>ERROR</loglevel>
      <recordtype>CASHSALE</recordtype>
      <runasrole>ADMINISTRATOR</runasrole>
      <status>RELEASED</status>
    </scriptdeployment>
    <scriptdeployment scriptid="customdeploy_ue_tran_bopis_check_est">
      <allemployees>F</allemployees>
      <alllocalizationcontexts>T</alllocalizationcontexts>
      <allpartners>F</allpartners>
      <allroles>T</allroles>
      <audslctrole>CUSTOMER_CENTER|EMPLOYEE_CENTER|NETSUITE_SUPPORT_CENTER__BASIC|NETSUITE_SUPPORT_CENTER|ONLINE_FORM_USER|PARTNER_CENTER|VENDOR_CENTER</audslctrole>
      <eventtype></eventtype>
      <executioncontext>ACTION|ADVANCEDREVREC|BANKCONNECTIVITY|BANKSTATEMENTPARSER|BUNDLEINSTALLATION|CLIENT|CONSOLRATEADJUSTOR|CSVIMPORT|CUSTOMGLLINES|CUSTOMMASSUPDATE|DATASETBUILDER|DEBUGGER|EMAILCAPTURE|FICONNECTIVITY|FIPARSER|MAPREDUCE|OCRPLUGIN|OTHER|PAYMENTGATEWAY|PAYMENTPOSTBACK|PLATFORMEXTENSION|PORTLET|PROMOTIONS|RECORDACTION|RESTLET|RESTWEBSERVICES|SCHEDULED|SDFINSTALLATION|SHIPPINGPARTNERS|SUITELET|TAXCALCULATION|USEREVENT|USERINTERFACE|WEBSERVICES|WORKBOOKBUILDER|WORKFLOW</executioncontext>
      <isdeployed>T</isdeployed>
      <loglevel>ERROR</loglevel>
      <recordtype>ESTIMATE</recordtype>
      <runasrole>ADMINISTRATOR</runasrole>
      <status>RELEASED</status>
    </scriptdeployment>
    <scriptdeployment scriptid="customdeploy_ue_tran_bopis_check_so">
      <allemployees>F</allemployees>
      <alllocalizationcontexts>T</alllocalizationcontexts>
      <allpartners>F</allpartners>
      <allroles>T</allroles>
      <audslctrole>CUSTOMER_CENTER|EMPLOYEE_CENTER|NETSUITE_SUPPORT_CENTER__BASIC|NETSUITE_SUPPORT_CENTER|ONLINE_FORM_USER|PARTNER_CENTER|VENDOR_CENTER</audslctrole>
      <eventtype></eventtype>
      <executioncontext>ACTION|ADVANCEDREVREC|BANKCONNECTIVITY|BANKSTATEMENTPARSER|BUNDLEINSTALLATION|CLIENT|CONSOLRATEADJUSTOR|CSVIMPORT|CUSTOMGLLINES|CUSTOMMASSUPDATE|DATASETBUILDER|DEBUGGER|EMAILCAPTURE|FICONNECTIVITY|FIPARSER|MAPREDUCE|OCRPLUGIN|OTHER|PAYMENTGATEWAY|PAYMENTPOSTBACK|PLATFORMEXTENSION|PORTLET|PROMOTIONS|RECORDACTION|RESTLET|RESTWEBSERVICES|SCHEDULED|SDFINSTALLATION|SHIPPINGPARTNERS|SUITELET|TAXCALCULATION|USEREVENT|USERINTERFACE|WEBSERVICES|WORKBOOKBUILDER|WORKFLOW</executioncontext>
      <isdeployed>T</isdeployed>
      <loglevel>ERROR</loglevel>
      <recordtype>SALESORDER</recordtype>
      <runasrole>ADMINISTRATOR</runasrole>
      <status>RELEASED</status>
    </scriptdeployment>
    <scriptdeployment scriptid="customdeploy_ue_tran_bopis_check_inv">
      <allemployees>F</allemployees>
      <alllocalizationcontexts>T</alllocalizationcontexts>
      <allpartners>F</allpartners>
      <allroles>T</allroles>
      <audslctrole>CUSTOMER_CENTER|EMPLOYEE_CENTER|NETSUITE_SUPPORT_CENTER__BASIC|NETSUITE_SUPPORT_CENTER|ONLINE_FORM_USER|PARTNER_CENTER|VENDOR_CENTER</audslctrole>
      <eventtype></eventtype>
      <executioncontext>ACTION|ADVANCEDREVREC|BANKCONNECTIVITY|BANKSTATEMENTPARSER|BUNDLEINSTALLATION|CLIENT|CONSOLRATEADJUSTOR|CSVIMPORT|CUSTOMGLLINES|CUSTOMMASSUPDATE|DATASETBUILDER|DEBUGGER|EMAILCAPTURE|FICONNECTIVITY|FIPARSER|MAPREDUCE|OCRPLUGIN|OTHER|PAYMENTGATEWAY|PAYMENTPOSTBACK|PLATFORMEXTENSION|PORTLET|PROMOTIONS|RECORDACTION|RESTLET|RESTWEBSERVICES|SCHEDULED|SDFINSTALLATION|SHIPPINGPARTNERS|SUITELET|TAXCALCULATION|USEREVENT|USERINTERFACE|WEBSERVICES|WORKBOOKBUILDER|WORKFLOW</executioncontext>
      <isdeployed>T</isdeployed>
      <loglevel>ERROR</loglevel>
      <recordtype>INVOICE</recordtype>
      <runasrole>ADMINISTRATOR</runasrole>
      <status>RELEASED</status>
    </scriptdeployment>
  </scriptdeployments>
</usereventscript>